hyperassist/__init__.py
hyperassist/log_assist/__init__.py
hyperassist/log_assist/analyzer.py
hyperassist/parameter_assist/__init__.py
hyperassist/parameter_assist/formula_registry.py
hyperassist/parameter_assist/suggestor.py
hyperassist/parameter_assist/utils.py
hyperassist/parameter_assist/validators.py
hyperassist/parameter_assist/formulas/__init__.py
hyperassist/parameter_assist/formulas/l1_heuristics.py
hyperassist/parameter_assist/formulas/l2_param_heuristics.py
hyperassist/parameter_assist/formulas/l3_semi_theoretical.py
hyperassist/parameter_assist/formulas/l4_theoretical.py
hyperassist/utils/color_utils.py
hyperassist-0.0.3.dist-info/licenses/LICENSE
test/test.py
hyperassist-0.0.3.dist-info/METADATA
hyperassist-0.0.3.dist-info/WHEEL
hyperassist-0.0.3.dist-info/top_level.txt
hyperassist-0.0.3.dist-info/RECORD
