Metadata-Version: 2.4
Name: hyperassist
Version: 0.0.3
Summary: AI training diagnostics and hyperparameter assistant.
Author-email: diputs-sudo <diputs-sudo@proton.me>
License-Expression: Apache-2.0
Project-URL: Homepage, https://pypi.org/project/hyperassist
Project-URL: Repository, https://github.com/diputs-sudo/hyperassist
Project-URL: Issues, https://github.com/diputs-sudo/hyperassist/issues
Requires-Python: >=3.9
License-File: LICENSE
Requires-Dist: numpy
Requires-Dist: psutil
Requires-Dist: scipy
Dynamic: license-file
